cloudinary_upload/__init__.py
cloudinary_upload-0.0.4.dist-info/LICENSE.txt
cloudinary_upload-0.0.4.dist-info/METADATA
cloudinary_upload-0.0.4.dist-info/WHEEL
cloudinary_upload-0.0.4.dist-info/top_level.txt
cloudinary_upload-0.0.4.dist-info/RECORD
