Metadata-Version: 2.1
Name: cloudinary-upload
Version: 0.0.4
Summary: Upload a signed image to cloudinary effectively
Home-page: https://github.com/faradayafrica/cloudinary-image-upload
License: CC0 1.0
Keywords: cloudinary,media asset
Platform: UNKNOWN
Classifier: Development Status :: 5 - Production/Stable
Classifier: Intended Audience :: Developers
Classifier: License :: CC0 1.0 Universal (CC0 1.0) Public Domain Dedication
Classifier: Programming Language :: Python :: 3
Requires-Dist: cloudinary
Requires-Dist: python-decouple
Requires-Dist: importlib-metadata ; python_version <= "3.9"
